aniplease/__init__.py
aniplease/category_types.py
aniplease/upload.py
aniplease-0.0.4.dist-info/METADATA
aniplease-0.0.4.dist-info/WHEEL
aniplease-0.0.4.dist-info/top_level.txt
aniplease-0.0.4.dist-info/RECORD
