Metadata-Version: 2.1
Name: aniplease
Version: 0.0.4
Author: EncodePlease Team
Author-email: encodeplease@proton.me
License: GNU AFFERO aa rha posts GENERAL PUBLIC LICENSE (v3)
Classifier: Programming Language :: Python :: 3
Classifier: Programming Language :: Python :: 3.7
Classifier: Programming Language :: Python :: 3.8
Classifier: Programming Language :: Python :: 3.9
Classifier: Programming Language :: Python :: 3.10
Classifier: Programming Language :: Python :: 3.11
Classifier: Programming Language :: Python :: 3.12
Classifier: License :: OSI Approved :: GNU General Public License v3 (GPLv3)
Classifier: Operating System :: OS Independent
Requires-Python: >=3.6
Requires-Dist: aiohttp
Requires-Dist: aiofiles
Requires-Dist: asyncio
Requires-Dist: requests
Requires-Dist: tqdm
